{
  "format_version": "1.8.0",
  "minecraft:client_entity": {
    "description": {
      "identifier": "mystic:axolotl",
      "materials": {
        "default": "axolotl",
        "water": "axolotl_water"
      },
      "textures": {
        "default": "textures/entity/axolotl",
        "water": "textures/entity/axolotl_water"
      },
      "geometry": {
        "default": "geometry.mob_axolotl"
      },
      "render_controllers": ["controller.render.axolotl"],
      "spawn_egg": {
        "base_color": "#42e5f4",
        "overlay_color": "#278ddb"
      }
    }
  }
}